surfgeo/__init__.py
surfgeo/client.py
surfgeo/payload.py
surfgeo/types.py
surfgeo/middleware/__init__.py
surfgeo/middleware/asgi.py
surfgeo/middleware/django.py
surfgeo/middleware/fastapi.py
surfgeo/middleware/flask.py
surfgeo/middleware/wsgi.py
surfgeo_sdk-1.0.1.dist-info/licenses/LICENSE
surfgeo_sdk-1.0.1.dist-info/METADATA
surfgeo_sdk-1.0.1.dist-info/WHEEL
surfgeo_sdk-1.0.1.dist-info/top_level.txt
surfgeo_sdk-1.0.1.dist-info/RECORD
