Metadata-Version: 2.4
Name: surfgeo-sdk
Version: 1.0.1
Summary: Server-side AI bot tracking SDK for Python
Home-page: https://github.com/thebisontech/surfgeo-python-aireferral-sdk
Author: surfgeo
Author-email: surfgeo <support@surfgeo.com>
License-Expression: MIT
Project-URL: Homepage, https://github.com/thebisontech/surfgeo-python-aireferral-sdk
Project-URL: Bug Tracker, https://github.com/thebisontech/surfgeo-python-aireferral-sdk/issues
Project-URL: Documentation, https://github.com/thebisontech/surfgeo-python-aireferral-sdk/blob/main/docs/README.md
Keywords: surfgeo,ai,bot,tracking,analytics
Classifier: Programming Language :: Python :: 3
Classifier: Operating System :: OS Independent
Requires-Python: >=3.8
License-File: LICENSE
Requires-Dist: requests>=2.25.0
Requires-Dist: httpx>=0.23.0
Provides-Extra: django
Requires-Dist: Django>=3.2; extra == "django"
Provides-Extra: flask
Requires-Dist: Flask>=2.0; extra == "flask"
Provides-Extra: fastapi
Requires-Dist: fastapi>=0.95.0; extra == "fastapi"
Requires-Dist: starlette>=0.26.0; extra == "fastapi"
Provides-Extra: dev
Requires-Dist: pytest>=7.0; extra == "dev"
Requires-Dist: pytest-asyncio>=0.20; extra == "dev"
Requires-Dist: pytest-cov>=4.0; extra == "dev"
Requires-Dist: black>=22.0; extra == "dev"
Requires-Dist: flake8>=5.0; extra == "dev"
Requires-Dist: mypy>=1.0; extra == "dev"
Dynamic: author
Dynamic: home-page
Dynamic: license-file
Dynamic: requires-python
